{
    "id": 62969628,
    "name": "Allegiance",
    "author": "Nikrodox",
    "creators": [],
    "verifier": "Riot",
    "verification": "https://www.youtube.com/watch?v=gW1mNW94lG4",
    "percentToQualify": 100,
    "records": [
        {
            "user": "RevueGD",
            "link": "https://www.youtube.com/watch?v=KM6Mo5whAKI&t=23s",
            "percent": 100,
            "hz": 360
        },
        {
            "user": "Bamvie",
            "link": "https://youtu.be/2HBBeOA9fSo",
            "percent": 100,
            "hz": 360
        }
    ]
}
